licenzy/__init__.py
licenzy/cli.py
licenzy/core.py
licenzy/management.py
licenzy-1.0.0.dist-info/METADATA
licenzy-1.0.0.dist-info/WHEEL
licenzy-1.0.0.dist-info/entry_points.txt
licenzy-1.0.0.dist-info/licenses/LICENSE
licenzy-1.0.0.dist-info/RECORD
