Metadata-Version: 2.4
Name: licenzy
Version: 1.0.0
Summary: 🔑 Simple, Pythonic license management for AI tools and indie projects
Project-URL: Homepage, https://github.com/yourusername/licenzy
Project-URL: Repository, https://github.com/yourusername/licenzy
Project-URL: Documentation, https://licenzy.readthedocs.io
Project-URL: Bug Tracker, https://github.com/yourusername/licenzy/issues
Author-email: Your Name <your.email@example.com>
License: MIT License
License-File: LICENSE
Keywords: ai,authentication,license,licensing,tools,validation
Classifier: Development Status :: 4 - Beta
Classifier: Intended Audience :: Developers
Classifier: License :: OSI Approved :: MIT License
Classifier: Programming Language :: Python :: 3
Classifier: Programming Language :: Python :: 3.8
Classifier: Programming Language :: Python :: 3.9
Classifier: Programming Language :: Python :: 3.10
Classifier: Programming Language :: Python :: 3.11
Classifier: Programming Language :: Python :: 3.12
Classifier: Topic :: Software Development :: Libraries :: Python Modules
Classifier: Topic :: System :: Systems Administration :: Authentication/Directory
Requires-Python: >=3.8
Requires-Dist: click>=8.0.0
Provides-Extra: dev
Requires-Dist: black>=22.0; extra == 'dev'
Requires-Dist: flake8>=4.0; extra == 'dev'
Requires-Dist: mypy>=0.950; extra == 'dev'
Requires-Dist: pytest-cov>=3.0; extra == 'dev'
Requires-Dist: pytest>=6.0; extra == 'dev'
